Metadata-Version: 1.0
Name: fuggetaboutit
Version: 0.3.3
Summary: implementations of a counting bloom filter, a timing bloom filter and a scaling timing bloom filter. ie: bloom filters for the stream
Home-page: http://github.com/mynameisfiber/fuggetaboutit/
Author: Micha Gorelick
Author-email: mynameisfiber@gmail.com
License: GNU Lesser General Public License v3 or later (LGPLv3+)
Download-URL: https://github.com/mynameisfiber/fuggetaboutit/tarball/master
Platform: UNKNOWN
Classifier: Programming Language :: Python
Classifier: Topic :: Scientific/Engineering
Classifier: Topic :: Software Development :: Libraries
Classifier: License :: OSI Approved :: GNU Lesser General Public License v3 or later (LGPLv3+)
